readmission_modelling/__init__.py
readmission_modelling/exploration_utilities.py
readmission_modelling/model_utilities.py
readmission_modelling/pdf.py
readmission_modelling/plotting_utilities.py
readmission_modelling/utilities.py
readmission_modelling-0.0.3.dist-info/METADATA
readmission_modelling-0.0.3.dist-info/WHEEL
readmission_modelling-0.0.3.dist-info/top_level.txt
readmission_modelling-0.0.3.dist-info/RECORD
