Metadata-Version: 2.1
Name: readmission_modelling
Version: 0.0.3
Summary: A package the modules to carry out the readmission modelling based on the patient's infomration and medical conditions
Author-email: Jed Beynon <jed.beynon@camgenium.com>
Project-URL: Homepage, https://github.com/pypa/sampleproject
Project-URL: Issues, https://github.com/pypa/sampleproject/issues
Classifier: Programming Language :: Python :: 3
Classifier: Operating System :: OS Independent
Requires-Python: >=3.8
